daydream/__init__.py
daydream/cli.py
daydream/mcp.py
daydream/models.py
daydream/utils.py
daydream/config/__init__.py
daydream/config/defaults.yaml
daydream/config/utils.py
daydream/knowledge/__init__.py
daydream/knowledge/edges.py
daydream/knowledge/graph.py
daydream/knowledge/nodes/__init__.py
daydream/knowledge/nodes/base.py
daydream/knowledge/nodes/mixins/__init__.py
daydream/knowledge/nodes/mixins/logs.py
daydream/knowledge/nodes/mixins/metrics.py
daydream/lib/__init__.py
daydream/lib/anomalies.py
daydream/lib/log_anomalies.py
daydream/plugins/__init__.py
daydream/plugins/base.py
daydream/plugins/aptible/__init__.py
daydream/plugins/aptible/client.py
daydream/plugins/aptible/logs.py
daydream/plugins/aptible/plugin.py
daydream/plugins/aptible/utils.py
daydream/plugins/aptible/nodes/__init__.py
daydream/plugins/aptible/nodes/aptible_app.py
daydream/plugins/aptible/nodes/aptible_aws_instance.py
daydream/plugins/aptible/nodes/aptible_container.py
daydream/plugins/aptible/nodes/aptible_custom_resource.py
daydream/plugins/aptible/nodes/aptible_database.py
daydream/plugins/aptible/nodes/aptible_deployment.py
daydream/plugins/aptible/nodes/aptible_disk.py
daydream/plugins/aptible/nodes/aptible_service.py
daydream/plugins/aptible/nodes/aptible_vhost.py
daydream/plugins/aptible/nodes/base.py
daydream/plugins/aws/__init__.py
daydream/plugins/aws/plugin.py
daydream/plugins/aws/utils.py
daydream/plugins/aws/nodes/__init__.py
daydream/plugins/aws/nodes/aws_alb_target_group.py
daydream/plugins/aws/nodes/aws_application_load_balancer.py
daydream/plugins/aws/nodes/aws_classic_load_balancer.py
daydream/plugins/aws/nodes/aws_ebs_volume.py
daydream/plugins/aws/nodes/aws_ec2_instance.py
daydream/plugins/aws/nodes/aws_rds_database.py
daydream/plugins/aws/nodes/base.py
daydream/plugins/core/__init__.py
daydream/plugins/core/plugin.py
daydream/plugins/graph/__init__.py
daydream/plugins/graph/plugin.py
daydream/plugins/logs/__init__.py
daydream/plugins/logs/plugin.py
daydream-0.1.0.dist-info/METADATA
daydream-0.1.0.dist-info/WHEEL
daydream-0.1.0.dist-info/entry_points.txt
daydream-0.1.0.dist-info/RECORD
