Metadata-Version: 2.4
Name: daydream
Version: 0.1.0
Summary: Add your description here
Requires-Python: >=3.12
Requires-Dist: aioboto3>=14.1.0
Requires-Dist: anyio>=4.9.0
Requires-Dist: boltons>=25.0.0
Requires-Dist: dnspython>=2.7.0
Requires-Dist: drain3>=0.9.11
Requires-Dist: fastmcp>=2.2.0
Requires-Dist: graphviz>=0.20.3
Requires-Dist: httpx>=0.28.1
Requires-Dist: logparser>=0.8.4
Requires-Dist: matplotlib>=3.10.1
Requires-Dist: networkx>=3.4.2
Requires-Dist: numpy<2.2
Requires-Dist: pydantic>=2.11.3
Requires-Dist: pydot>=3.0.4
Requires-Dist: pyod==2.0.3
Requires-Dist: pythonping>=1.1.4
Requires-Dist: pyyaml>=6.0.2
Requires-Dist: requests>=2.32.3
Requires-Dist: scapy>=2.6.1
Requires-Dist: sh>=2.2.2
Requires-Dist: sparklines>=0.5.0
Requires-Dist: typer>=0.15.2
Requires-Dist: whoosh-reloaded>=2.7.5
